linrax/__init__.py
linrax/optim.py
linrax-2025.2.1.dist-info/METADATA
linrax-2025.2.1.dist-info/WHEEL
linrax-2025.2.1.dist-info/RECORD
