Metadata-Version: 2.4
Name: linrax
Version: 2025.2.1
Summary: A JAX-compatible, simplex method-based linear program solver
Project-URL: Repository, https://github.com/gtfactslab/linrax.git
Requires-Python: >=3.11
Requires-Dist: jax~=0.4.35
Provides-Extra: cuda
Requires-Dist: jax[cuda12-pip]~=0.4.35; extra == 'cuda'
Provides-Extra: examples
Requires-Dist: cvxpy~=1.5.3; extra == 'examples'
Requires-Dist: gurobipy~=12.0.0; extra == 'examples'
Requires-Dist: jaxopt~=0.8.3; extra == 'examples'
Requires-Dist: matplotlib~=3.9.2; extra == 'examples'
Requires-Dist: scipy~=1.14.1; extra == 'examples'
